MANIFEST.in
Makefile
README
setup.cfg
setup.py
test/__init__.py
test/__init__.pyc
test/test_remotebag.py
test/__pycache__/test_remotebag.cpython-27-PYTEST.pyc
tiddlywebplugins/__init__.py
tiddlywebplugins/remotebag.py
tiddlywebplugins.remotebag.egg-info/PKG-INFO
tiddlywebplugins.remotebag.egg-info/SOURCES.txt
tiddlywebplugins.remotebag.egg-info/dependency_links.txt
tiddlywebplugins.remotebag.egg-info/namespace_packages.txt
tiddlywebplugins.remotebag.egg-info/not-zip-safe
tiddlywebplugins.remotebag.egg-info/requires.txt
tiddlywebplugins.remotebag.egg-info/top_level.txt