Metadata-Version: 1.0
Name: tiddlywebplugins.remotebag
Version: 0.7
Summary: Access remote content as a bag
Home-page: http://pypi.python.org/pypi/tiddlywebplugins.remotebag
Author: Chris Dent
Author-email: cdent@peermore.com
License: UNKNOWN
Platform: Posix; MacOS X; Windows
